{
    "history_all": {
        "labels": [
            "25-feb",
            "26-feb",
            "27-feb",
            "28-feb",
            "01-mrt",
            "02-mrt",
            "03-mrt",
            "04-mrt",
            "05-mrt",
            "06-mrt",
            "07-mrt",
            "08-mrt",
            "09-mrt",
            "10-mrt",
            "11-mrt",
            "12-mrt",
            "13-mrt",
            "14-mrt",
            "15-mrt",
            "16-mrt",
            "17-mrt",
            "18-mrt",
            "19-mrt",
            "20-mrt",
            "21-mrt",
            "22-mrt",
            "23-mrt",
            "24-mrt",
            "25-mrt",
            "26-mrt",
            "27-mrt",
            "28-mrt",
            "29-mrt"
        ],
        "population": 529247,
        "minimum_one_dose": 44011,
        "first_dose": 27700,
        "second_dose": 16311,
        "diff_7_minimum_one_dose": 8305,
        "diff_7_second_dose": 1710,
        "timeseries_minimum_one_dose": [
            15064,
            15064,
            15064,
            15069,
            17843,
            18271,
            18855,
            21284,
            22952,
            23308,
            23497,
            23735,
            23996,
            24464,
            25306,
            25651,
            25721,
            25737,
            27810,
            29682,
            29888,
            31720,
            34334,
            34435,
            34716,
            35706,
            37852,
            39479,
            41198,
            42758,
            43445,
            43512,
            44011
        ],
        "timeseries_second_dose": [
            10018,
            10018,
            10018,
            10157,
            11218,
            11438,
            11551,
            11678,
            11701,
            11706,
            11712,
            11725,
            11803,
            11896,
            12095,
            12351,
            12419,
            12555,
            12652,
            12729,
            12986,
            13491,
            14250,
            14342,
            14347,
            14601,
            15052,
            15376,
            15857,
            16081,
            16098,
            16214,
            16311
        ],
        "timeseries_percentage_minimum_one_dose": [
            2.85,
            2.85,
            2.85,
            2.85,
            3.37,
            3.45,
            3.56,
            4.02,
            4.34,
            4.4,
            4.44,
            4.48,
            4.53,
            4.62,
            4.78,
            4.85,
            4.86,
            4.86,
            5.25,
            5.61,
            5.65,
            5.99,
            6.49,
            6.51,
            6.56,
            6.75,
            7.15,
            7.46,
            7.78,
            8.08,
            8.21,
            8.22,
            8.32
        ],
        "timeseries_percentage_second_dose": [
            1.89,
            1.89,
            1.89,
            1.92,
            2.12,
            2.16,
            2.18,
            2.21,
            2.21,
            2.21,
            2.21,
            2.22,
            2.23,
            2.25,
            2.29,
            2.33,
            2.35,
            2.37,
            2.39,
            2.41,
            2.45,
            2.55,
            2.69,
            2.71,
            2.71,
            2.76,
            2.84,
            2.91,
            3.0,
            3.04,
            3.04,
            3.06,
            3.08
        ]
    },
    "history_adults": {
        "labels": [
            "25-feb",
            "26-feb",
            "27-feb",
            "28-feb",
            "01-mrt",
            "02-mrt",
            "03-mrt",
            "04-mrt",
            "05-mrt",
            "06-mrt",
            "07-mrt",
            "08-mrt",
            "09-mrt",
            "10-mrt",
            "11-mrt",
            "12-mrt",
            "13-mrt",
            "14-mrt",
            "15-mrt",
            "16-mrt",
            "17-mrt",
            "18-mrt",
            "19-mrt",
            "20-mrt",
            "21-mrt",
            "22-mrt",
            "23-mrt",
            "24-mrt",
            "25-mrt",
            "26-mrt",
            "27-mrt",
            "28-mrt",
            "29-mrt"
        ],
        "population": 409350,
        "minimum_one_dose": 43991,
        "first_dose": 27696,
        "second_dose": 16295,
        "diff_7_minimum_one_dose": 8304,
        "diff_7_second_dose": 1710,
        "timeseries_minimum_one_dose": [
            15047,
            15047,
            15047,
            15052,
            17826,
            18254,
            18838,
            21267,
            22935,
            23291,
            23480,
            23718,
            23978,
            24446,
            25288,
            25632,
            25702,
            25718,
            27791,
            29663,
            29869,
            31701,
            34315,
            34416,
            34697,
            35687,
            37833,
            39459,
            41178,
            42738,
            43425,
            43492,
            43991
        ],
        "timeseries_second_dose": [
            10008,
            10008,
            10008,
            10147,
            11204,
            11424,
            11537,
            11664,
            11687,
            11692,
            11698,
            11711,
            11789,
            11880,
            12079,
            12335,
            12403,
            12539,
            12636,
            12713,
            12970,
            13475,
            14234,
            14326,
            14331,
            14585,
            15036,
            15360,
            15841,
            16065,
            16082,
            16198,
            16295
        ],
        "timeseries_percentage_minimum_one_dose": [
            3.68,
            3.68,
            3.68,
            3.68,
            4.35,
            4.46,
            4.6,
            5.2,
            5.6,
            5.69,
            5.74,
            5.79,
            5.86,
            5.97,
            6.18,
            6.26,
            6.28,
            6.28,
            6.79,
            7.25,
            7.3,
            7.74,
            8.38,
            8.41,
            8.48,
            8.72,
            9.24,
            9.64,
            10.06,
            10.44,
            10.61,
            10.62,
            10.75
        ],
        "timeseries_percentage_second_dose": [
            2.44,
            2.44,
            2.44,
            2.48,
            2.74,
            2.79,
            2.82,
            2.85,
            2.86,
            2.86,
            2.86,
            2.86,
            2.88,
            2.9,
            2.95,
            3.01,
            3.03,
            3.06,
            3.09,
            3.11,
            3.17,
            3.29,
            3.48,
            3.5,
            3.5,
            3.56,
            3.67,
            3.75,
            3.87,
            3.92,
            3.93,
            3.96,
            3.98
        ]
    },
    "per_age": {
        "labels": [
            "80+",
            "60-79",
            "40-59",
            "20-39",
            "0-19"
        ],
        "population": [
            28360,
            85483,
            129137,
            155118,
            131149
        ],
        "first_dose": [
            9515,
            7348,
            5176,
            5605,
            56
        ],
        "second_dose": [
            4480,
            3096,
            4476,
            4151,
            108
        ],
        "percentage_first_dose": [
            33.55,
            8.6,
            4.01,
            3.61,
            0.04
        ],
        "percentage_second_dose": [
            15.8,
            3.62,
            3.47,
            2.68,
            0.08
        ]
    },
    "municipality": "Antwerpen",
    "province": "Antwerpen",
    "zone": "Antwerpen Centrum-Noord-Oost-Zuid",
    "inhabitants": "Antwerpenaars",
    "last_date": "29/03/2021",
    "date_diff_7": "22/03/2021"
}