{
    "history_all": {
        "labels": [
            "24-feb",
            "25-feb",
            "26-feb",
            "27-feb",
            "28-feb",
            "01-mrt",
            "02-mrt",
            "03-mrt",
            "04-mrt",
            "05-mrt",
            "06-mrt",
            "07-mrt",
            "08-mrt",
            "09-mrt",
            "10-mrt"
        ],
        "population": 8529,
        "minimum_one_dose": 577,
        "first_dose": 202,
        "second_dose": 375,
        "timeseries_minimum_one_dose": [
            0,
            418,
            418,
            418,
            418,
            447,
            454,
            463,
            510,
            522,
            548,
            560,
            564,
            564,
            577
        ],
        "timeseries_second_dose": [
            0,
            340,
            340,
            340,
            341,
            359,
            364,
            365,
            367,
            367,
            367,
            367,
            370,
            372,
            375
        ],
        "timeseries_percentage_minimum_one_dose": [
            0,
            4.9,
            4.9,
            4.9,
            4.9,
            5.24,
            5.32,
            5.43,
            5.98,
            6.12,
            6.43,
            6.57,
            6.61,
            6.61,
            6.77
        ],
        "timeseries_percentage_second_dose": [
            0,
            3.99,
            3.99,
            3.99,
            4.0,
            4.21,
            4.27,
            4.28,
            4.3,
            4.3,
            4.3,
            4.3,
            4.34,
            4.36,
            4.4
        ]
    },
    "history_adults": {
        "labels": [
            "24-feb",
            "25-feb",
            "26-feb",
            "27-feb",
            "28-feb",
            "01-mrt",
            "02-mrt",
            "03-mrt",
            "04-mrt",
            "05-mrt",
            "06-mrt",
            "07-mrt",
            "08-mrt",
            "09-mrt",
            "10-mrt"
        ],
        "population": 6816,
        "minimum_one_dose": 576,
        "first_dose": 202,
        "second_dose": 374,
        "timeseries_minimum_one_dose": [
            0,
            417,
            417,
            417,
            417,
            446,
            453,
            462,
            509,
            521,
            547,
            559,
            563,
            563,
            576
        ],
        "timeseries_second_dose": [
            0,
            339,
            339,
            339,
            340,
            358,
            363,
            364,
            366,
            366,
            366,
            366,
            369,
            371,
            374
        ],
        "timeseries_percentage_minimum_one_dose": [
            0,
            6.12,
            6.12,
            6.12,
            6.12,
            6.54,
            6.65,
            6.78,
            7.47,
            7.64,
            8.03,
            8.2,
            8.26,
            8.26,
            8.45
        ],
        "timeseries_percentage_second_dose": [
            0,
            4.97,
            4.97,
            4.97,
            4.99,
            5.25,
            5.33,
            5.34,
            5.37,
            5.37,
            5.37,
            5.37,
            5.41,
            5.44,
            5.49
        ]
    },
    "per_age": {
        "labels": [
            "80+",
            "60-79",
            "40-59",
            "20-39",
            "0-19"
        ],
        "population": [
            496,
            1824,
            2386,
            1938,
            1885
        ],
        "first_dose": [
            8,
            40,
            99,
            55,
            0
        ],
        "second_dose": [
            119,
            73,
            96,
            81,
            6
        ],
        "percentage_first_dose": [
            1.61,
            2.19,
            4.15,
            2.84,
            0.0
        ],
        "percentage_second_dose": [
            23.99,
            4.0,
            4.02,
            4.18,
            0.32
        ]
    },
    "last_date": "10/03/2021"
}