{
    "history_all": {
        "labels": [
            "25-feb",
            "26-feb",
            "27-feb",
            "28-feb",
            "01-mrt",
            "02-mrt",
            "03-mrt",
            "04-mrt",
            "05-mrt",
            "06-mrt",
            "07-mrt",
            "08-mrt",
            "09-mrt",
            "10-mrt",
            "11-mrt",
            "12-mrt",
            "13-mrt",
            "14-mrt",
            "15-mrt",
            "16-mrt",
            "17-mrt",
            "18-mrt",
            "19-mrt",
            "20-mrt",
            "21-mrt",
            "22-mrt",
            "23-mrt",
            "24-mrt",
            "25-mrt",
            "26-mrt",
            "27-mrt",
            "28-mrt",
            "29-mrt",
            "30-mrt",
            "31-mrt",
            "01-apr",
            "02-apr",
            "03-apr",
            "04-apr",
            "05-apr",
            "06-apr",
            "07-apr",
            "08-apr",
            "09-apr",
            "10-apr",
            "11-apr",
            "12-apr",
            "13-apr",
            "14-apr",
            "15-apr",
            "16-apr",
            "17-apr",
            "18-apr",
            "19-apr",
            "20-apr",
            "21-apr",
            "22-apr",
            "23-apr",
            "24-apr",
            "25-apr",
            "26-apr",
            "27-apr",
            "28-apr"
        ],
        "population": 22813,
        "minimum_one_dose": 5432,
        "first_dose": 3889,
        "second_dose": 1543,
        "diff_7_minimum_one_dose": 713,
        "diff_7_second_dose": 12,
        "timeseries_minimum_one_dose": [
            891,
            891,
            891,
            896,
            1119,
            1124,
            1185,
            1262,
            1328,
            1336,
            1340,
            1343,
            1394,
            1404,
            1477,
            1579,
            1588,
            1603,
            1603,
            1622,
            1626,
            1627,
            1647,
            1650,
            1650,
            1651,
            1651,
            1656,
            1936,
            2150,
            2152,
            2152,
            2214,
            2219,
            2357,
            2557,
            2670,
            2672,
            2672,
            2672,
            2676,
            2677,
            3035,
            3037,
            3327,
            3618,
            3624,
            3624,
            3630,
            3630,
            3630,
            4067,
            4067,
            4067,
            4718,
            4719,
            4721,
            5165,
            5432,
            5432,
            5432,
            5432,
            5432
        ],
        "timeseries_second_dose": [
            695,
            695,
            695,
            695,
            734,
            752,
            753,
            769,
            776,
            776,
            776,
            776,
            778,
            798,
            806,
            823,
            825,
            825,
            825,
            825,
            834,
            886,
            924,
            989,
            989,
            994,
            1002,
            1003,
            1065,
            1108,
            1113,
            1117,
            1124,
            1162,
            1162,
            1223,
            1258,
            1278,
            1278,
            1282,
            1299,
            1298,
            1300,
            1309,
            1309,
            1312,
            1313,
            1313,
            1313,
            1319,
            1319,
            1514,
            1514,
            1514,
            1531,
            1531,
            1531,
            1537,
            1540,
            1540,
            1540,
            1540,
            1543
        ],
        "timeseries_percentage_minimum_one_dose": [
            3.91,
            3.91,
            3.91,
            3.93,
            4.91,
            4.93,
            5.19,
            5.53,
            5.82,
            5.86,
            5.87,
            5.89,
            6.11,
            6.15,
            6.47,
            6.92,
            6.96,
            7.03,
            7.03,
            7.11,
            7.13,
            7.13,
            7.22,
            7.23,
            7.23,
            7.24,
            7.24,
            7.26,
            8.49,
            9.42,
            9.43,
            9.43,
            9.7,
            9.73,
            10.33,
            11.21,
            11.7,
            11.71,
            11.71,
            11.71,
            11.73,
            11.73,
            13.3,
            13.31,
            14.58,
            15.86,
            15.89,
            15.89,
            15.91,
            15.91,
            15.91,
            17.83,
            17.83,
            17.83,
            20.68,
            20.69,
            20.69,
            22.64,
            23.81,
            23.81,
            23.81,
            23.81,
            23.81
        ],
        "timeseries_percentage_second_dose": [
            3.05,
            3.05,
            3.05,
            3.05,
            3.22,
            3.3,
            3.3,
            3.37,
            3.4,
            3.4,
            3.4,
            3.4,
            3.41,
            3.5,
            3.53,
            3.61,
            3.62,
            3.62,
            3.62,
            3.62,
            3.66,
            3.88,
            4.05,
            4.34,
            4.34,
            4.36,
            4.39,
            4.4,
            4.67,
            4.86,
            4.88,
            4.9,
            4.93,
            5.09,
            5.09,
            5.36,
            5.51,
            5.6,
            5.6,
            5.62,
            5.69,
            5.69,
            5.7,
            5.74,
            5.74,
            5.75,
            5.76,
            5.76,
            5.76,
            5.78,
            5.78,
            6.64,
            6.64,
            6.64,
            6.71,
            6.71,
            6.71,
            6.74,
            6.75,
            6.75,
            6.75,
            6.75,
            6.76
        ]
    },
    "history_adults": {
        "labels": [
            "25-feb",
            "26-feb",
            "27-feb",
            "28-feb",
            "01-mrt",
            "02-mrt",
            "03-mrt",
            "04-mrt",
            "05-mrt",
            "06-mrt",
            "07-mrt",
            "08-mrt",
            "09-mrt",
            "10-mrt",
            "11-mrt",
            "12-mrt",
            "13-mrt",
            "14-mrt",
            "15-mrt",
            "16-mrt",
            "17-mrt",
            "18-mrt",
            "19-mrt",
            "20-mrt",
            "21-mrt",
            "22-mrt",
            "23-mrt",
            "24-mrt",
            "25-mrt",
            "26-mrt",
            "27-mrt",
            "28-mrt",
            "29-mrt",
            "30-mrt",
            "31-mrt",
            "01-apr",
            "02-apr",
            "03-apr",
            "04-apr",
            "05-apr",
            "06-apr",
            "07-apr",
            "08-apr",
            "09-apr",
            "10-apr",
            "11-apr",
            "12-apr",
            "13-apr",
            "14-apr",
            "15-apr",
            "16-apr",
            "17-apr",
            "18-apr",
            "19-apr",
            "20-apr",
            "21-apr",
            "22-apr",
            "23-apr",
            "24-apr",
            "25-apr",
            "26-apr",
            "27-apr",
            "28-apr"
        ],
        "population": 18409,
        "minimum_one_dose": 5426,
        "first_dose": 3889,
        "second_dose": 1537,
        "diff_7_minimum_one_dose": 713,
        "diff_7_second_dose": 12,
        "timeseries_minimum_one_dose": [
            886,
            886,
            886,
            891,
            1114,
            1119,
            1180,
            1257,
            1322,
            1330,
            1334,
            1337,
            1388,
            1398,
            1471,
            1573,
            1582,
            1597,
            1597,
            1616,
            1620,
            1621,
            1641,
            1644,
            1644,
            1645,
            1645,
            1650,
            1930,
            2144,
            2146,
            2146,
            2208,
            2213,
            2351,
            2551,
            2664,
            2666,
            2666,
            2666,
            2670,
            2671,
            3029,
            3031,
            3321,
            3612,
            3618,
            3618,
            3624,
            3624,
            3624,
            4061,
            4061,
            4061,
            4712,
            4713,
            4715,
            5159,
            5426,
            5426,
            5426,
            5426,
            5426
        ],
        "timeseries_second_dose": [
            694,
            694,
            694,
            694,
            733,
            749,
            750,
            766,
            773,
            773,
            773,
            773,
            775,
            795,
            803,
            820,
            822,
            822,
            822,
            822,
            829,
            881,
            919,
            984,
            984,
            989,
            997,
            998,
            1060,
            1102,
            1107,
            1111,
            1118,
            1156,
            1156,
            1217,
            1252,
            1272,
            1272,
            1276,
            1293,
            1292,
            1294,
            1303,
            1303,
            1306,
            1307,
            1307,
            1307,
            1313,
            1313,
            1508,
            1508,
            1508,
            1525,
            1525,
            1525,
            1531,
            1534,
            1534,
            1534,
            1534,
            1537
        ],
        "timeseries_percentage_minimum_one_dose": [
            4.81,
            4.81,
            4.81,
            4.84,
            6.05,
            6.08,
            6.41,
            6.83,
            7.18,
            7.22,
            7.25,
            7.26,
            7.54,
            7.59,
            7.99,
            8.54,
            8.59,
            8.68,
            8.68,
            8.78,
            8.8,
            8.81,
            8.91,
            8.93,
            8.93,
            8.94,
            8.94,
            8.96,
            10.48,
            11.65,
            11.66,
            11.66,
            11.99,
            12.02,
            12.77,
            13.86,
            14.47,
            14.48,
            14.48,
            14.48,
            14.5,
            14.51,
            16.45,
            16.46,
            18.04,
            19.62,
            19.65,
            19.65,
            19.69,
            19.69,
            19.69,
            22.06,
            22.06,
            22.06,
            25.6,
            25.6,
            25.61,
            28.02,
            29.47,
            29.47,
            29.47,
            29.47,
            29.47
        ],
        "timeseries_percentage_second_dose": [
            3.77,
            3.77,
            3.77,
            3.77,
            3.98,
            4.07,
            4.07,
            4.16,
            4.2,
            4.2,
            4.2,
            4.2,
            4.21,
            4.32,
            4.36,
            4.45,
            4.47,
            4.47,
            4.47,
            4.47,
            4.5,
            4.79,
            4.99,
            5.35,
            5.35,
            5.37,
            5.42,
            5.42,
            5.76,
            5.99,
            6.01,
            6.04,
            6.07,
            6.28,
            6.28,
            6.61,
            6.8,
            6.91,
            6.91,
            6.93,
            7.02,
            7.02,
            7.03,
            7.08,
            7.08,
            7.09,
            7.1,
            7.1,
            7.1,
            7.13,
            7.13,
            8.19,
            8.19,
            8.19,
            8.28,
            8.28,
            8.28,
            8.32,
            8.33,
            8.33,
            8.33,
            8.33,
            8.35
        ]
    },
    "per_age": {
        "labels": [
            "80+",
            "60-79",
            "40-59",
            "20-39",
            "0-19"
        ],
        "population": [
            1280,
            4668,
            6595,
            5401,
            4869
        ],
        "first_dose": [
            951,
            2181,
            375,
            371,
            11
        ],
        "second_dose": [
            339,
            240,
            543,
            400,
            21
        ],
        "percentage_first_dose": [
            74.3,
            46.72,
            5.69,
            6.87,
            0.23
        ],
        "percentage_second_dose": [
            26.48,
            5.14,
            8.23,
            7.41,
            0.43
        ]
    },
    "location": "Balen",
    "province": "Antwerpen",
    "zone": "Baldemore",
    "inhabitants": "Balenaars",
    "last_date": "28/04/2021",
    "date_diff_7": "21/04/2021"
}